[
  {
    "PathogenName":"Escherichia coli",
    "AntibioticName":"Carbapenems",
    "exposure_records":8,
    "total_bcis":2137559.0,
    "exposure_score":1.0
  },
  {
    "PathogenName":"Escherichia coli",
    "AntibioticName":"Third-generation cephalosporins",
    "exposure_records":8,
    "total_bcis":2137559.0,
    "exposure_score":1.0
  },
  {
    "PathogenName":"Staphylococcus aureus",
    "AntibioticName":"Methicillin resistance",
    "exposure_records":8,
    "total_bcis":1047305.0,
    "exposure_score":0.4899537276
  },
  {
    "PathogenName":"Klebsiella pneumoniae",
    "AntibioticName":"Carbapenems",
    "exposure_records":8,
    "total_bcis":812339.0,
    "exposure_score":0.3800311477
  },
  {
    "PathogenName":"Klebsiella pneumoniae",
    "AntibioticName":"Third-generation cephalosporins",
    "exposure_records":8,
    "total_bcis":812339.0,
    "exposure_score":0.3800311477
  },
  {
    "PathogenName":"Acinetobacter spp.",
    "AntibioticName":"Carbapenems",
    "exposure_records":8,
    "total_bcis":233333.0,
    "exposure_score":0.1091586244
  },
  {
    "PathogenName":"Streptococcus pneumoniae",
    "AntibioticName":"Penicillins",
    "exposure_records":8,
    "total_bcis":150274.0,
    "exposure_score":0.0703016852
  },
  {
    "PathogenName":"Salmonella spp.",
    "AntibioticName":"Fluoroquinolones",
    "exposure_records":8,
    "total_bcis":70727.0,
    "exposure_score":0.0330877417
  }
]